transformation.py
cfn_transform-1.1.0.dist-info/METADATA
cfn_transform-1.1.0.dist-info/WHEEL
cfn_transform-1.1.0.dist-info/entry_points.txt
cfn_transform-1.1.0.dist-info/top_level.txt
cfn_transform-1.1.0.dist-info/RECORD
