Metadata-Version: 2.1
Name: cfn-transform
Version: 1.1.0
Home-page: https://github.com/trek10inc/cfn-transform
Author: Trek10, Inc
Author-email: package-management@trek10.com
License: MIT
Requires-Dist: cfn-lint ~=0.83.2
Requires-Dist: click ==7.1.2
